libjacobi-abb-driver.so
jacobi_driver_abb.cpython-310-x86_64-linux-gnu.so
jacobi_abb_driver.libs/libboost_system-69a6c43e.so.1.66.0
jacobi_abb_driver.libs/libcurl-19cca934.so.4.8.0
jacobi_abb_driver.libs/libcrypto-bfee2032.so.1.1.1k
jacobi_abb_driver.libs/libcpr-62807a53.so.1.11.0
jacobi_abb_driver.libs/libprotobuf-36a8ac49.so.15.0.0
jacobi_abb_driver.libs/libssl-658e53cd.so.1.1.1k
lib64/libcurl.so.4
lib64/libcpr.so
lib64/libcurl.so.4.8.0
lib64/libcpr.so.1.11.0
lib64/libcurl.so
lib64/libcpr.so.1
lib64/cmake/CURL/CURLTargets-release.cmake
lib64/cmake/CURL/CURLConfig.cmake
lib64/cmake/CURL/CURLTargets.cmake
lib64/cmake/CURL/CURLConfigVersion.cmake
lib64/cmake/cpr/cprTargets.cmake
lib64/cmake/cpr/cprTargets-release.cmake
lib64/pkgconfig/libcurl.pc
jacobi_abb_driver-1.1.21.dist-info/METADATA
jacobi_abb_driver-1.1.21.dist-info/WHEEL
jacobi_abb_driver-1.1.21.dist-info/RECORD
jacobi_abb_driver-1.1.21.dist-info/licenses/LICENSE
share/man/man1/curl-config.1
share/man/man1/mk-ca-bundle.1
share/man/man3/CURLINFO_CONDITION_UNMET.3
share/man/man3/CURLMOPT_PIPELINING_SITE_BL.3
share/man/man3/CURLINFO_SIZE_DOWNLOAD_T.3
share/man/man3/CURLOPT_CONV_FROM_UTF8_FUNCTION.3
share/man/man3/CURLOPT_FTP_ACCOUNT.3
share/man/man3/CURLOPT_TIMECONDITION.3
share/man/man3/CURLOPT_SOCKS5_GSSAPI_NEC.3
share/man/man3/CURLOPT_POSTFIELDSIZE_LARGE.3
share/man/man3/CURLOPT_SSH_KNOWNHOSTS.3
share/man/man3/CURLOPT_USERPWD.3
share/man/man3/CURLOPT_XFERINFOFUNCTION.3
share/man/man3/CURLOPT_AUTOREFERER.3
share/man/man3/CURLOPT_READFUNCTION.3
share/man/man3/curl_mime_addpart.3
share/man/man3/CURLOPT_IOCTLDATA.3
share/man/man3/CURLOPT_TCP_KEEPIDLE.3
share/man/man3/CURLOPT_RESOLVER_START_FUNCTION.3
share/man/man3/CURLOPT_SERVER_RESPONSE_TIMEOUT.3
share/man/man3/CURLOPT_PROXYPORT.3
share/man/man3/CURLMOPT_PIPELINING_SERVER_BL.3
share/man/man3/CURLOPT_SSL_FALSESTART.3
share/man/man3/CURLINFO_FILETIME_T.3
share/man/man3/CURLOPT_SSL_OPTIONS.3
share/man/man3/CURLOPT_SSL_VERIFYSTATUS.3
share/man/man3/CURLINFO_PRIMARY_IP.3
share/man/man3/CURLINFO_SIZE_UPLOAD_T.3
share/man/man3/CURLOPT_COOKIEFILE.3
share/man/man3/CURLINFO_LOCAL_IP.3
